{
    "Robot":[
        {
            "rbt_id": 1,
            "mac_addr": "00:00:00:00:00:00"
        },
        {
            "rbt_id": 2,
            "mac_addr": "01:01:01:01:01:01"
        },
        {
            "rbt_id": 3,
            "mac_addr": "02:02:02:02:02:02"
        },
        {
            "rbt_id": 4,
            "mac_addr": "03:03:03:03:03:03"
        },
        {
            "rbt_id": 5,
            "mac_addr": "04:04:04:04:04:04"
        },
        {
            "rbt_id": 6,
            "mac_addr": "05:05:05:05:05:05"
        },
        {
            "rbt_id": 7,
            "mac_addr": "06:06:06:06:06:06"
        },
        {
            "rbt_id": 8,
            "mac_addr": "07:07:07:07:07:07"
        },
        {
            "rbt_id": 9,
            "mac_addr": "08:08:08:08:08:08"
        },
        {
            "rbt_id": 10,
            "mac_addr": "09:09:09:09:09:09"
        }
    ],
    "User":[
        {
            "uid": 1,
            "urbt_id": 1,
            "uname": "dolly",
            "password": "00000000",
            "email": "dolly0@radionoise.co",
            "phone": null
        },
        {
            "uid": 2,
            "urbt_id": 2,
            "uname": "last_order",
            "password": "lastorder20001",
            "email": "last_order20001@radionoise.co",
            "phone": null
        },
        {
            "uid": 3,
            "urbt_id": 4,
            "uname": "lester",
            "password": "abc456789",
            "email": "lester4869@protonmail.com",
            "phone": "0629310903"
        },
        {
            "uid": 4,
            "urbt_id": 5,
            "uname": "vermouth",
            "password": "0464759045",
            "email": "dolly0@blackorg.com",
            "phone": "0965484169"
        },
        {
            "uid": 5,
            "urbt_id": 3,
            "uname": "chianti",
            "password": "d_viper300",
            "email": "chianti300@blackorg.com",
            "phone": "0925300053"
        },
        {
            "uid": 6,
            "urbt_id": 7,
            "uname": "rum",
            "password": "sushi256",
            "email": "dolly0@blackorg.com",
            "phone": "0607502562"
        },
        {
            "uid": 7,
            "urbt_id": 6,
            "uname": "gin",
            "password": "p_356a1955",
            "email": "gin43680@blackorg.com",
            "phone": "0594869076"
        },
        {
            "uid": 8,
            "urbt_id": 8,
            "uname": "davidson",
            "password": "v-rod2003",
            "email": "davidson20030@blackorg.com",
            "phone": "0772733088"
        },
        {
            "uid": 9,
            "urbt_id": 9,
            "uname": "bourbon",
            "password": "fd_rx-7330",
            "email": "zero7310@blackorg.com",
            "phone": "0733100099"
        },
        {
            "uid": 10,
            "urbt_id": 10,
            "uname": "martini",
            "password": "aptx4869",
            "email": "martin4869@blackorg.com",
            "phone": "0486900010"
        }
    ]
}